drow/__init__.py
drow/annotation.py
drow/converter.py
drow/model.py
drow/parser.py
drow/py.typed
drow/query.py
drow-0.0.1.dist-info/METADATA
drow-0.0.1.dist-info/WHEEL
drow-0.0.1.dist-info/top_level.txt
drow-0.0.1.dist-info/RECORD
