Metadata-Version: 2.4
Name: drow
Version: 0.0.1
Summary: data model for Prometheus Query Language
Author: Elephant Liu
License-Expression: MIT
Project-URL: Homepage, https://github.com/xospc/drow
Classifier: Programming Language :: Python :: 3
Requires-Python: >=3.10
